{"charData":[{"top":294,"left":435.5,"width":12,"height":20},{"top":294,"left":447.5,"width":10,"height":20},{"top":294,"left":457.5,"width":10,"height":20},{"top":294,"left":467.5,"width":10,"height":20},{"top":294,"left":477.5,"width":4,"height":20},{"top":294,"left":481.484375,"width":10,"height":20},{"top":294,"left":491.484375,"width":8,"height":20},{"top":294,"left":499.484375,"width":15,"height":20},{"top":294,"left":514.46875,"width":10,"height":20},{"top":294,"left":524.46875,"width":9,"height":20},{"top":294,"left":533.46875,"width":9,"height":20},{"top":294,"left":542.46875,"width":5,"height":20},{"top":294,"left":547.46875,"width":10,"height":20},{"top":294,"left":557.46875,"width":4,"height":20},{"top":294,"left":561.453125,"width":10,"height":20},{"top":294,"left":571.453125,"width":9,"height":20},{"top":294,"left":580.453125,"width":9,"height":20},{"top":294,"left":589.453125,"width":5,"height":20},{"top":294,"left":594.453125,"width":10,"height":20},{"top":294,"left":604.453125,"width":10,"height":20},{"top":294,"left":614.453125,"width":4,"height":20},{"top":294,"left":618.4375,"width":6,"height":20},{"top":294,"left":624.421875,"width":9,"height":20},{"top":294,"left":633.421875,"width":10,"height":20},{"top":294,"left":643.421875,"width":10,"height":20},{"top":294,"left":653.421875,"width":6,"height":20},{"top":294,"left":659.40625,"width":9,"height":20},{"top":294,"left":668.40625,"width":10,"height":20},{"top":294,"left":678.40625,"width":10,"height":20},{"top":294,"left":688.40625,"width":10,"height":20},{"top":294,"left":698.40625,"width":4,"height":20},{"top":294,"left":702.390625,"width":9,"height":20},{"top":294,"left":711.390625,"width":9,"height":20},{"top":294,"left":720.390625,"width":4,"height":20},{"top":294,"left":724.375,"width":5,"height":20},{"top":294,"left":729.375,"width":10,"height":20},{"top":294,"left":739.375,"width":10,"height":20},{"top":294,"left":749.375,"width":5,"height":20},{"top":294,"left":754.375,"width":4,"height":20},{"top":294,"left":758.359375,"width":10,"height":20},{"top":294,"left":768.359375,"width":10,"height":20},{"top":294,"left":778.359375,"width":9,"height":20},{"top":294,"left":787.359375,"width":4,"height":20},{"top":294,"left":791.34375,"width":9,"height":20},{"top":294,"left":800.34375,"width":9,"height":20},{"top":294,"left":809.34375,"width":10,"height":20},{"top":294,"left":819.34375,"width":10,"height":20},{"top":294,"left":829.34375,"width":5,"height":20},{"top":294,"left":834.34375,"width":5,"height":20},{"top":294,"left":839.34375,"width":10,"height":20},{"top":294,"left":849.34375,"width":6,"height":20},{"top":294,"left":855.328125,"width":0,"height":0},{"top":319,"left":435.5,"width":5,"height":20},{"top":319,"left":440.5,"width":10,"height":20},{"top":319,"left":450.5,"width":10,"height":20},{"top":319,"left":460.5,"width":10,"height":20},{"top":319,"left":470.5,"width":6,"height":20},{"top":319,"left":476.5,"width":10,"height":20},{"top":319,"left":486.5,"width":9,"height":20},{"top":319,"left":495.5,"width":10,"height":20},{"top":319,"left":505.5,"width":10,"height":20},{"top":319,"left":515.5,"width":10,"height":20},{"top":319,"left":525.5,"width":15,"height":20},{"top":319,"left":540.484375,"width":4,"height":20},{"top":319,"left":544.46875,"width":9,"height":20},{"top":319,"left":553.46875,"width":6,"height":20},{"top":319,"left":559.46875,"width":9,"height":20},{"top":319,"left":568.46875,"width":10,"height":20},{"top":319,"left":578.46875,"width":10,"height":20},{"top":319,"left":588.46875,"width":10,"height":20},{"top":319,"left":598.46875,"width":4,"height":20},{"top":319,"left":602.453125,"width":5,"height":20},{"top":319,"left":607.453125,"width":4,"height":20},{"top":319,"left":611.4375,"width":10,"height":20},{"top":319,"left":621.4375,"width":10,"height":20},{"top":319,"left":631.4375,"width":9,"height":20},{"top":319,"left":640.4375,"width":6,"height":20},{"top":319,"left":646.4375,"width":4,"height":20},{"top":319,"left":650.421875,"width":10,"height":20},{"top":319,"left":660.421875,"width":6,"height":20},{"top":319,"left":666.421875,"width":5,"height":20},{"top":319,"left":671.421875,"width":10,"height":20},{"top":319,"left":681.421875,"width":10,"height":20},{"top":319,"left":691.421875,"width":4,"height":20},{"top":319,"left":695.40625,"width":6,"height":20},{"top":319,"left":701.390625,"width":7,"height":20},{"top":319,"left":708.390625,"width":10,"height":20},{"top":319,"left":718.390625,"width":10,"height":20},{"top":319,"left":728.390625,"width":5,"height":20},{"top":319,"left":733.390625,"width":4,"height":20},{"top":319,"left":737.375,"width":10,"height":20},{"top":319,"left":747.375,"width":10,"height":20},{"top":319,"left":757.375,"width":5,"height":20},{"top":319,"left":762.375,"width":7,"height":20},{"top":319,"left":769.375,"width":10,"height":20},{"top":319,"left":779.375,"width":10,"height":20},{"top":319,"left":789.375,"width":5,"height":20},{"top":319,"left":794.375,"width":7,"height":20},{"top":319,"left":801.375,"width":10,"height":20},{"top":319,"left":811.375,"width":10,"height":20},{"top":319,"left":821.375,"width":4,"height":20},{"top":319,"left":825.359375,"width":9,"height":20},{"top":319,"left":834.359375,"width":7,"height":20},{"top":319,"left":841.359375,"width":4,"height":20},{"top":319,"left":845.34375,"width":10,"height":20},{"top":319,"left":855.34375,"width":0,"height":0},{"top":344,"left":435.5,"width":12,"height":20},{"top":344,"left":447.5,"width":6,"height":20},{"top":344,"left":453.484375,"width":10,"height":20},{"top":344,"left":463.484375,"width":9,"height":20},{"top":344,"left":472.484375,"width":4,"height":20},{"top":344,"left":476.46875,"width":4,"height":20},{"top":344,"left":480.453125,"width":9,"height":20},{"top":344,"left":489.453125,"width":6,"height":20},{"top":344,"left":495.4375,"width":10,"height":20},{"top":344,"left":505.4375,"width":10,"height":20},{"top":344,"left":515.4375,"width":16,"height":20},{"top":344,"left":531.4375,"width":6,"height":20},{"top":344,"left":537.421875,"width":9,"height":20},{"top":344,"left":546.421875,"width":10,"height":20},{"top":344,"left":556.421875,"width":10,"height":20},{"top":344,"left":566.421875,"width":10,"height":20},{"top":344,"left":576.421875,"width":9,"height":20},{"top":344,"left":585.421875,"width":13,"height":20},{"top":344,"left":598.40625,"width":10,"height":20},{"top":344,"left":608.40625,"width":4,"height":20},{"top":344,"left":612.390625,"width":10,"height":20},{"top":344,"left":622.390625,"width":10,"height":20},{"top":344,"left":632.390625,"width":9,"height":20},{"top":344,"left":641.390625,"width":6,"height":20},{"top":344,"left":647.375,"width":10,"height":20},{"top":344,"left":657.375,"width":10,"height":20},{"top":344,"left":667.375,"width":16,"height":20},{"top":344,"left":683.375,"width":6,"height":20},{"top":344,"left":689.359375,"width":9,"height":20},{"top":344,"left":698.359375,"width":10,"height":20},{"top":344,"left":708.359375,"width":10,"height":20},{"top":344,"left":718.359375,"width":10,"height":20},{"top":344,"left":728.359375,"width":4,"height":20},{"top":344,"left":732.34375,"width":10,"height":20},{"top":344,"left":742.34375,"width":6,"height":20},{"top":344,"left":748.328125,"width":10,"height":20},{"top":344,"left":758.328125,"width":10,"height":20},{"top":344,"left":768.328125,"width":10,"height":20},{"top":344,"left":778.328125,"width":15,"height":20},{"top":344,"left":793.3125,"width":10,"height":20},{"top":344,"left":803.3125,"width":4,"height":20},{"top":344,"left":807.296875,"width":10,"height":20},{"top":344,"left":817.296875,"width":6,"height":20},{"top":344,"left":823.28125,"width":4,"height":20},{"top":344,"left":827.265625,"width":5,"height":20},{"top":344,"left":832.265625,"width":4,"height":20},{"top":344,"left":836.25,"width":10,"height":20},{"top":344,"left":846.25,"width":9,"height":20},{"top":344,"left":855.25,"width":0,"height":0},{"top":369,"left":435.5,"width":5,"height":20},{"top":369,"left":440.5,"width":10,"height":20},{"top":369,"left":450.5,"width":4,"height":20},{"top":369,"left":454.484375,"width":10,"height":20},{"top":369,"left":464.484375,"width":9,"height":20},{"top":369,"left":473.484375,"width":6,"height":20},{"top":369,"left":479.484375,"width":5,"height":20},{"top":369,"left":484.484375,"width":10,"height":20},{"top":369,"left":494.484375,"width":10,"height":20},{"top":369,"left":504.484375,"width":4,"height":20},{"top":369,"left":508.46875,"width":6,"height":20},{"top":369,"left":514.453125,"width":6,"height":20},{"top":369,"left":520.453125,"width":5,"height":20},{"top":369,"left":525.453125,"width":10,"height":20},{"top":369,"left":535.453125,"width":15,"height":20},{"top":369,"left":550.4375,"width":4,"height":20},{"top":369,"left":554.421875,"width":4,"height":20},{"top":369,"left":558.40625,"width":4,"height":20},{"top":369,"left":562.390625,"width":10,"height":20},{"top":369,"left":572.390625,"width":9,"height":20},{"top":369,"left":581.390625,"width":6,"height":20},{"top":369,"left":587.390625,"width":10,"height":20},{"top":369,"left":597.390625,"width":6,"height":20},{"top":369,"left":603.375,"width":10,"height":20},{"top":369,"left":613.375,"width":6,"height":20},{"top":369,"left":619.375,"width":10,"height":20},{"top":369,"left":629.375,"width":10,"height":20},{"top":369,"left":639.375,"width":5,"height":20},{"top":369,"left":644.375,"width":5,"height":20},{"top":369,"left":649.375,"width":10,"height":20},{"top":369,"left":659.375,"width":6,"height":20},{"top":369,"left":665.359375,"width":6,"height":20},{"top":369,"left":671.359375,"width":10,"height":20},{"top":369,"left":681.359375,"width":5,"height":20},{"top":369,"left":686.359375,"width":5,"height":20},{"top":369,"left":691.359375,"width":7,"height":20},{"top":369,"left":698.359375,"width":5,"height":20},{"top":369,"left":703.359375,"width":10,"height":20},{"top":369,"left":713.359375,"width":10,"height":20},{"top":369,"left":723.359375,"width":10,"height":20},{"top":369,"left":733.359375,"width":7,"height":20},{"top":369,"left":740.359375,"width":5,"height":20},{"top":369,"left":745.359375,"width":10,"height":20},{"top":369,"left":755.359375,"width":10,"height":20},{"top":369,"left":765.359375,"width":9,"height":20},{"top":369,"left":774.359375,"width":7,"height":20},{"top":369,"left":781.359375,"width":13,"height":20},{"top":369,"left":794.34375,"width":10,"height":20},{"top":369,"left":804.34375,"width":6,"height":20},{"top":369,"left":810.328125,"width":10,"height":20},{"top":369,"left":820.328125,"width":7,"height":20},{"top":369,"left":827.328125,"width":5,"height":20},{"top":369,"left":832.328125,"width":4,"height":20},{"top":369,"left":836.3125,"width":9,"height":20},{"top":369,"left":845.3125,"width":10,"height":20},{"top":369,"left":855.3125,"width":0,"height":0},{"top":394,"left":435.5,"width":9,"height":20},{"top":394,"left":444.5,"width":10,"height":20},{"top":394,"left":454.5,"width":10,"height":20},{"top":394,"left":464.5,"width":6,"height":20},{"top":394,"left":470.484375,"width":9,"height":20},{"top":394,"left":479.484375,"width":9,"height":20},{"top":394,"left":488.484375,"width":10,"height":20},{"top":394,"left":498.484375,"width":10,"height":20},{"top":394,"left":508.484375,"width":10,"height":20},{"top":394,"left":518.484375,"width":5,"height":20},{"top":394,"left":523.484375,"width":9,"height":20},{"top":394,"left":532.484375,"width":14,"height":20},{"top":394,"left":546.484375,"width":10,"height":20},{"top":394,"left":556.484375,"width":10,"height":20},{"top":394,"left":566.484375,"width":10,"height":20},{"top":394,"left":576.484375,"width":10,"height":20},{"top":394,"left":586.484375,"width":4,"height":20},{"top":394,"left":590.46875,"width":10,"height":20},{"top":394,"left":600.46875,"width":10,"height":20},{"top":394,"left":610.46875,"width":9,"height":20},{"top":394,"left":619.46875,"width":10,"height":20},{"top":394,"left":629.46875,"width":5,"height":20},{"top":394,"left":634.46875,"width":10,"height":20},{"top":394,"left":644.46875,"width":5,"height":20},{"top":394,"left":649.46875,"width":10,"height":20},{"top":394,"left":659.46875,"width":10,"height":20},{"top":394,"left":669.46875,"width":4,"height":20},{"top":394,"left":673.453125,"width":10,"height":20},{"top":394,"left":683.453125,"width":10,"height":20},{"top":394,"left":693.453125,"width":9,"height":20},{"top":394,"left":702.453125,"width":10,"height":20},{"top":394,"left":712.453125,"width":6,"height":20},{"top":394,"left":718.4375,"width":10,"height":20},{"top":394,"left":728.4375,"width":10,"height":20},{"top":394,"left":738.4375,"width":16,"height":20},{"top":394,"left":754.4375,"width":6,"height":20},{"top":394,"left":760.421875,"width":10,"height":20},{"top":394,"left":770.421875,"width":10,"height":20},{"top":394,"left":780.421875,"width":10,"height":20},{"top":394,"left":790.421875,"width":10,"height":20},{"top":394,"left":800.421875,"width":10,"height":20},{"top":394,"left":810.421875,"width":11,"height":20},{"top":394,"left":821.40625,"width":10,"height":20},{"top":394,"left":831.40625,"width":6,"height":20},{"top":394,"left":837.390625,"width":9,"height":20},{"top":394,"left":846.390625,"width":9,"height":20},{"top":394,"left":855.390625,"width":0,"height":0},{"top":419,"left":435.5,"width":6,"height":20},{"top":419,"left":441.484375,"width":10,"height":20},{"top":419,"left":451.484375,"width":10,"height":20},{"top":419,"left":461.484375,"width":16,"height":20},{"top":419,"left":477.484375,"width":6,"height":20},{"top":419,"left":483.46875,"width":13,"height":20},{"top":419,"left":496.46875,"width":10,"height":20},{"top":419,"left":506.46875,"width":4,"height":20},{"top":419,"left":510.453125,"width":9,"height":20},{"top":419,"left":519.453125,"width":10,"height":20},{"top":419,"left":529.453125,"width":13,"height":20},{"top":419,"left":542.453125,"width":9,"height":20},{"top":419,"left":551.453125,"width":10,"height":20},{"top":419,"left":561.453125,"width":9,"height":20},{"top":419,"left":570.453125,"width":14,"height":20},{"top":419,"left":584.453125,"width":5,"height":20},{"top":419,"left":589.453125,"width":10,"height":20},{"top":419,"left":599.453125,"width":10,"height":20},{"top":419,"left":609.453125,"width":4,"height":20},{"top":419,"left":613.4375,"width":6,"height":20},{"top":419,"left":619.421875,"width":14,"height":20},{"top":419,"left":633.421875,"width":9,"height":20},{"top":419,"left":642.421875,"width":4,"height":20},{"top":419,"left":646.40625,"width":5,"height":20},{"top":419,"left":651.40625,"width":10,"height":20},{"top":419,"left":661.40625,"width":10,"height":20},{"top":419,"left":671.40625,"width":5,"height":20},{"top":419,"left":676.40625,"width":4,"height":20},{"top":419,"left":680.390625,"width":10,"height":20},{"top":419,"left":690.390625,"width":10,"height":20},{"top":419,"left":700.390625,"width":9,"height":20},{"top":419,"left":709.390625,"width":14,"height":20},{"top":419,"left":723.390625,"width":10,"height":20},{"top":419,"left":733.390625,"width":10,"height":20},{"top":419,"left":743.390625,"width":9,"height":20},{"top":419,"left":752.390625,"width":10,"height":20},{"top":419,"left":762.390625,"width":14,"height":20},{"top":419,"left":776.390625,"width":4,"height":20},{"top":419,"left":780.375,"width":15,"height":20},{"top":419,"left":795.359375,"width":10,"height":20},{"top":419,"left":805.359375,"width":6,"height":20},{"top":419,"left":811.34375,"width":10,"height":20},{"top":419,"left":821.34375,"width":9,"height":20},{"top":419,"left":830.34375,"width":10,"height":20},{"top":419,"left":840.34375,"width":10,"height":20},{"top":419,"left":850.34375,"width":5,"height":20},{"top":419,"left":855.34375,"width":0,"height":0},{"top":444,"left":435.5,"width":13,"height":20},{"top":444,"left":448.484375,"width":10,"height":20},{"top":444,"left":458.484375,"width":13,"height":20},{"top":444,"left":471.46875,"width":10,"height":20},{"top":444,"left":481.46875,"width":9,"height":20},{"top":444,"left":490.46875,"width":10,"height":20},{"top":444,"left":500.46875,"width":6,"height":20},{"top":444,"left":506.453125,"width":5,"height":20},{"top":444,"left":511.453125,"width":9,"height":20},{"top":444,"left":520.453125,"width":15,"height":20},{"top":444,"left":535.4375,"width":10,"height":20},{"top":444,"left":545.4375,"width":4,"height":20},{"top":444,"left":549.421875,"width":10,"height":20},{"top":444,"left":559.421875,"width":6,"height":20},{"top":444,"left":565.40625,"width":4,"height":20},{"top":444,"left":569.390625,"width":5,"height":20},{"top":444,"left":574.390625,"width":4,"height":20},{"top":444,"left":578.375,"width":10,"height":20},{"top":444,"left":588.375,"width":9,"height":20},{"top":444,"left":597.375,"width":9,"height":20},{"top":444,"left":606.375,"width":10,"height":20},{"top":444,"left":616.375,"width":6,"height":20},{"top":444,"left":622.359375,"width":9,"height":20},{"top":444,"left":631.359375,"width":10,"height":20},{"top":444,"left":641.359375,"width":4,"height":20},{"top":444,"left":645.34375,"width":10,"height":20},{"top":444,"left":655.34375,"width":6,"height":20},{"top":444,"left":661.328125,"width":10,"height":20},{"top":444,"left":671.328125,"width":4,"height":20},{"top":444,"left":675.3125,"width":4,"height":20},{"top":444,"left":679.296875,"width":5,"height":20},{"top":444,"left":684.296875,"width":4,"height":20},{"top":444,"left":688.28125,"width":10,"height":20},{"top":444,"left":698.28125,"width":9,"height":20},{"top":444,"left":707.28125,"width":9,"height":20},{"top":444,"left":716.28125,"width":4,"height":20},{"top":444,"left":720.265625,"width":10,"height":20},{"top":444,"left":730.265625,"width":9,"height":20},{"top":444,"left":739.265625,"width":10,"height":20},{"top":444,"left":749.265625,"width":10,"height":20},{"top":444,"left":759.265625,"width":10,"height":20},{"top":444,"left":769.265625,"width":10,"height":20},{"top":444,"left":779.265625,"width":5,"height":20},{"top":444,"left":784.265625,"width":4,"height":20},{"top":444,"left":788.25,"width":10,"height":20},{"top":444,"left":798.25,"width":10,"height":20},{"top":444,"left":808.25,"width":9,"height":20},{"top":444,"left":817.25,"width":10,"height":20},{"top":444,"left":827.25,"width":9,"height":20},{"top":444,"left":836.25,"width":10,"height":20},{"top":444,"left":846.25,"width":9,"height":20},{"top":444,"left":855.25,"width":0,"height":0},{"top":469,"left":435.5,"width":5,"height":20},{"top":469,"left":440.5,"width":10,"height":20},{"top":469,"left":450.5,"width":10,"height":20},{"top":469,"left":460.5,"width":4,"height":20},{"top":469,"left":464.484375,"width":6,"height":20},{"top":469,"left":470.46875,"width":5,"height":20},{"top":469,"left":475.46875,"width":5,"height":20},{"top":469,"left":480.46875,"width":10,"height":20},{"top":469,"left":490.46875,"width":15,"height":20},{"top":469,"left":505.453125,"width":4,"height":20},{"top":469,"left":509.4375,"width":4,"height":20},{"top":469,"left":513.421875,"width":9,"height":20},{"top":469,"left":522.421875,"width":6,"height":20},{"top":469,"left":528.421875,"width":5,"height":20},{"top":469,"left":533.421875,"width":4,"height":20},{"top":469,"left":537.40625,"width":10,"height":20},{"top":469,"left":547.40625,"width":10,"height":20},{"top":469,"left":557.40625,"width":10,"height":20},{"top":469,"left":567.40625,"width":9,"height":20},{"top":469,"left":576.40625,"width":4,"height":20},{"top":469,"left":580.390625,"width":10,"height":20},{"top":469,"left":590.390625,"width":4,"height":20},{"top":469,"left":594.375,"width":6,"height":20},{"top":469,"left":600.375,"width":9,"height":20},{"top":469,"left":609.375,"width":4,"height":20},{"top":469,"left":613.359375,"width":5,"height":20},{"top":469,"left":618.359375,"width":10,"height":20},{"top":469,"left":628.359375,"width":10,"height":20},{"top":469,"left":638.359375,"width":5,"height":20},{"top":469,"left":643.359375,"width":4,"height":20},{"top":469,"left":647.34375,"width":10,"height":20},{"top":469,"left":657.34375,"width":10,"height":20},{"top":469,"left":667.34375,"width":6,"height":20},{"top":469,"left":673.34375,"width":10,"height":20},{"top":469,"left":683.34375,"width":10,"height":20},{"top":469,"left":693.34375,"width":9,"height":20},{"top":469,"left":702.34375,"width":6,"height":20},{"top":469,"left":708.34375,"width":10,"height":20},{"top":469,"left":718.34375,"width":10,"height":20},{"top":469,"left":728.34375,"width":5,"height":20},{"top":469,"left":733.34375,"width":10,"height":20},{"top":469,"left":743.34375,"width":6,"height":20},{"top":469,"left":749.328125,"width":4,"height":20},{"top":469,"left":753.3125,"width":10,"height":20},{"top":469,"left":763.3125,"width":6,"height":20},{"top":469,"left":769.296875,"width":10,"height":20},{"top":469,"left":779.296875,"width":5,"height":20},{"top":469,"left":784.296875,"width":10,"height":20},{"top":469,"left":794.296875,"width":10,"height":20},{"top":469,"left":804.296875,"width":5,"height":20},{"top":469,"left":809.296875,"width":6,"height":20},{"top":469,"left":815.296875,"width":12,"height":20},{"top":469,"left":827.296875,"width":10,"height":20},{"top":469,"left":837.296875,"width":4,"height":20},{"top":469,"left":841.28125,"width":4,"height":20},{"top":469,"left":845.265625,"width":10,"height":20},{"top":469,"left":855.265625,"width":0,"height":0},{"top":494,"left":435.5,"width":15,"height":20},{"top":494,"left":450.484375,"width":10,"height":20},{"top":494,"left":460.484375,"width":4,"height":20},{"top":494,"left":464.46875,"width":10,"height":20},{"top":494,"left":474.46875,"width":6,"height":20},{"top":494,"left":480.453125,"width":4,"height":20},{"top":494,"left":484.4375,"width":5,"height":20},{"top":494,"left":489.4375,"width":4,"height":20},{"top":494,"left":493.421875,"width":10,"height":20},{"top":494,"left":503.421875,"width":9,"height":20},{"top":494,"left":512.421875,"width":10,"height":20},{"top":494,"left":522.421875,"width":10,"height":20},{"top":494,"left":532.421875,"width":10,"height":20},{"top":494,"left":542.421875,"width":4,"height":20},{"top":494,"left":546.40625,"width":10,"height":20},{"top":494,"left":556.40625,"width":10,"height":20},{"top":494,"left":566.40625,"width":5,"height":20},{"top":494,"left":571.40625,"width":10,"height":20},{"top":494,"left":581.40625,"width":4,"height":20},{"top":494,"left":585.390625,"width":9,"height":20},{"top":494,"left":594.390625,"width":10,"height":20},{"top":494,"left":604.390625,"width":9,"height":20},{"top":494,"left":613.390625,"width":4,"height":20},{"top":494,"left":617.375,"width":10,"height":20},{"top":494,"left":627.375,"width":13,"height":20},{"top":494,"left":640.359375,"width":10,"height":20},{"top":494,"left":650.359375,"width":4,"height":20},{"top":494,"left":654.34375,"width":10,"height":20},{"top":494,"left":664.34375,"width":11,"height":20},{"top":494,"left":675.34375,"width":14,"height":20},{"top":494,"left":689.34375,"width":6,"height":20},{"top":494,"left":695.328125,"width":10,"height":20},{"top":494,"left":705.328125,"width":10,"height":20},{"top":494,"left":715.328125,"width":9,"height":20},{"top":494,"left":724.328125,"width":10,"height":20},{"top":494,"left":734.328125,"width":11,"height":20},{"top":494,"left":745.328125,"width":6,"height":20},{"top":494,"left":751.3125,"width":10,"height":20},{"top":494,"left":761.3125,"width":10,"height":20},{"top":494,"left":771.3125,"width":16,"height":20},{"top":494,"left":787.3125,"width":6,"height":20},{"top":494,"left":793.296875,"width":5,"height":20},{"top":494,"left":798.296875,"width":11,"height":20},{"top":494,"left":809.296875,"width":12,"height":20},{"top":494,"left":821.296875,"width":10,"height":20},{"top":494,"left":831.296875,"width":10,"height":20},{"top":494,"left":841.296875,"width":4,"height":20},{"top":494,"left":845.28125,"width":10,"height":20},{"top":494,"left":855.28125,"width":0,"height":0},{"top":519,"left":435.5,"width":6,"height":20},{"top":519,"left":441.484375,"width":10,"height":20},{"top":519,"left":451.484375,"width":10,"height":20},{"top":519,"left":461.484375,"width":16,"height":20},{"top":519,"left":477.484375,"width":6,"height":20},{"top":519,"left":483.46875,"width":5,"height":20},{"top":519,"left":488.46875,"width":10,"height":20},{"top":519,"left":498.46875,"width":10,"height":20},{"top":519,"left":508.46875,"width":10,"height":20},{"top":519,"left":518.46875,"width":5,"height":20},{"top":519,"left":523.46875,"width":12,"height":20},{"top":519,"left":535.46875,"width":10,"height":20},{"top":519,"left":545.46875,"width":9,"height":20},{"top":519,"left":554.46875,"width":4,"height":20},{"top":519,"left":558.453125,"width":9,"height":20},{"top":519,"left":567.453125,"width":5,"height":20},{"top":519,"left":572.453125,"width":10,"height":20},{"top":519,"left":582.453125,"width":10,"height":20},{"top":519,"left":592.453125,"width":6,"height":20},{"top":519,"left":598.453125,"width":6,"height":20},{"top":519,"left":604.4375,"width":10,"height":20},{"top":519,"left":614.4375,"width":10,"height":20},{"top":519,"left":624.4375,"width":16,"height":20},{"top":519,"left":640.4375,"width":6,"height":20},{"top":519,"left":646.421875,"width":5,"height":20},{"top":519,"left":651.421875,"width":6,"height":20},{"top":519,"left":657.421875,"width":10,"height":20},{"top":519,"left":667.421875,"width":9,"height":20},{"top":519,"left":676.421875,"width":6,"height":20},{"top":519,"left":682.421875,"width":10,"height":20},{"top":519,"left":692.421875,"width":10,"height":20},{"top":519,"left":702.421875,"width":6,"height":20},{"top":519,"left":708.421875,"width":10,"height":20},{"top":519,"left":718.421875,"width":5,"height":20},{"top":519,"left":723.421875,"width":6,"height":20},{"top":519,"left":729.421875,"width":4,"height":20},{"top":519,"left":733.40625,"width":10,"height":20},{"top":519,"left":743.40625,"width":10,"height":20},{"top":519,"left":753.40625,"width":9,"height":20},{"top":519,"left":762.40625,"width":5,"height":20},{"top":519,"left":767.40625,"width":6,"height":20},{"top":519,"left":773.40625,"width":5,"height":20},{"top":519,"left":778.40625,"width":10,"height":20},{"top":519,"left":788.40625,"width":10,"height":20},{"top":519,"left":798.40625,"width":6,"height":20},{"top":519,"left":804.390625,"width":6,"height":20},{"top":519,"left":810.375,"width":4,"height":20},{"top":519,"left":814.359375,"width":10,"height":20},{"top":519,"left":824.359375,"width":6,"height":20},{"top":519,"left":830.34375,"width":5,"height":20},{"top":519,"left":835.34375,"width":10,"height":20},{"top":519,"left":845.34375,"width":10,"height":20},{"top":519,"left":855.34375,"width":0,"height":0},{"top":544,"left":435.5,"width":4,"height":20},{"top":544,"left":439.484375,"width":10,"height":20},{"top":544,"left":449.484375,"width":16,"height":20},{"top":544,"left":465.484375,"width":10,"height":20},{"top":544,"left":475.484375,"width":10,"height":20},{"top":544,"left":485.484375,"width":10,"height":20},{"top":544,"left":495.484375,"width":10,"height":20},{"top":544,"left":505.484375,"width":10,"height":20},{"top":544,"left":515.484375,"width":10,"height":20},{"top":544,"left":525.484375,"width":10,"height":20},{"top":544,"left":535.484375,"width":5,"height":20},{"top":544,"left":540.484375,"width":16,"height":20},{"top":544,"left":556.484375,"width":5,"height":20},{"top":544,"left":561.484375,"width":5,"height":20},{"top":544,"left":566.484375,"width":10,"height":20},{"top":544,"left":576.484375,"width":4,"height":20},{"top":544,"left":580.46875,"width":9,"height":20},{"top":544,"left":589.46875,"width":5,"height":20},{"top":544,"left":594.46875,"width":17,"height":20},{"top":544,"left":611.46875,"width":11,"height":20},{"top":544,"left":622.453125,"width":6,"height":20},{"top":544,"left":628.4375,"width":10,"height":20},{"top":544,"left":638.4375,"width":10,"height":20},{"top":544,"left":648.4375,"width":9,"height":20},{"top":544,"left":657.4375,"width":10,"height":20},{"top":544,"left":667.4375,"width":5,"height":20},{"top":544,"left":672.4375,"width":17,"height":20},{"top":544,"left":689.4375,"width":12,"height":20},{"top":544,"left":701.4375,"width":6,"height":20},{"top":544,"left":707.421875,"width":4,"height":20},{"top":544,"left":711.40625,"width":5,"height":20},{"top":544,"left":716.40625,"width":10,"height":20},{"top":544,"left":726.40625,"width":4,"height":20},{"top":544,"left":730.390625,"width":10,"height":20},{"top":544,"left":740.390625,"width":5,"height":20},{"top":544,"left":745.390625,"width":17,"height":20},{"top":544,"left":762.390625,"width":5,"height":20},{"top":544,"left":767.390625,"width":10,"height":20},{"top":544,"left":777.390625,"width":10,"height":20},{"top":544,"left":787.390625,"width":17,"height":20},{"top":544,"left":804.390625,"width":13,"height":20},{"top":544,"left":817.375,"width":9,"height":20},{"top":544,"left":826.375,"width":10,"height":20},{"top":544,"left":836.375,"width":9,"height":20},{"top":544,"left":845.375,"width":10,"height":20},{"top":544,"left":855.375,"width":0,"height":0},{"top":569,"left":435.5,"width":13,"height":20},{"top":569,"left":448.484375,"width":10,"height":20},{"top":569,"left":458.484375,"width":10,"height":20},{"top":569,"left":468.484375,"width":10,"height":20},{"top":569,"left":478.484375,"width":10,"height":20},{"top":569,"left":488.484375,"width":4,"height":20},{"top":569,"left":492.46875,"width":4,"height":20},{"top":569,"left":496.453125,"width":9,"height":20},{"top":569,"left":505.453125,"width":5,"height":20},{"top":569,"left":510.453125,"width":5,"height":20},{"top":569,"left":515.453125,"width":9,"height":20},{"top":569,"left":524.453125,"width":10,"height":20},{"top":569,"left":534.453125,"width":10,"height":20},{"top":569,"left":544.453125,"width":10,"height":20},{"top":569,"left":554.453125,"width":10,"height":20},{"top":569,"left":564.453125,"width":5,"height":20},{"top":569,"left":569.453125,"width":5,"height":20},{"top":569,"left":574.453125,"width":12,"height":20},{"top":569,"left":586.453125,"width":10,"height":20},{"top":569,"left":596.453125,"width":9,"height":20},{"top":569,"left":605.453125,"width":10,"height":20},{"top":569,"left":615.453125,"width":5,"height":20},{"top":569,"left":620.453125,"width":5,"height":20},{"top":569,"left":625.453125,"width":10,"height":20},{"top":569,"left":635.453125,"width":10,"height":20},{"top":569,"left":645.453125,"width":10,"height":20},{"top":569,"left":655.453125,"width":5,"height":20},{"top":569,"left":660.453125,"width":12,"height":20},{"top":569,"left":672.453125,"width":10,"height":20},{"top":569,"left":682.453125,"width":4,"height":20},{"top":569,"left":686.4375,"width":10,"height":20},{"top":569,"left":696.4375,"width":10,"height":20},{"top":569,"left":706.4375,"width":10,"height":20},{"top":569,"left":716.4375,"width":5,"height":20}],"sentenceData":[{"sentence":"People may think their personal situation is better than economic conditions in their nation, but only in Brazil (72%) and China (70%) do large majorities think their families are better off than they were five years ago.","start":0,"end":220,"numofwords":37,"polygonCoords":[{"x":435.5,"y":294},{"x":435.5,"y":314},{"x":435.5,"y":314},{"x":435.5,"y":414},{"x":523.484375,"y":414},{"x":523.484375,"y":394},{"x":855.5,"y":394},{"x":855.5,"y":294}]},{"sentence":" On balance, Indians (50%) and Turks (43%) also say their situations have improved.","start":221,"end":303,"numofwords":14,"polygonCoords":[{"x":523.484375,"y":394},{"x":523.484375,"y":414},{"x":435.5,"y":414},{"x":435.5,"y":439},{"x":855.34375,"y":439},{"x":855.34375,"y":419},{"x":855.5,"y":419},{"x":855.5,"y":394}]},{"sentence":" However, majorities or pluralities in 9 nations say their family financial situation has deteriorated.","start":304,"end":406,"numofwords":15,"polygonCoords":[{"x":855.34375,"y":419},{"x":855.34375,"y":419},{"x":435.5,"y":419},{"x":435.5,"y":489},{"x":809.296875,"y":489},{"x":809.296875,"y":469},{"x":854.5,"y":469},{"x":854.5,"y":444}]},{"sentence":" Solid majorities hold this view in Greece (81%), Spain (60%) and Pakistan (57%), as do at least four-in-ten in Lebanon, Italy, France, Britain, the Czech Republic, Japan, Egypt and Poland.","start":407,"end":595,"numofwords":31,"polygonCoords":[{"x":809.296875,"y":469},{"x":809.296875,"y":489},{"x":435.5,"y":489},{"x":435.5,"y":589},{"x":721.4375,"y":589},{"x":721.4375,"y":569},{"x":855.5,"y":569},{"x":855.5,"y":469}]}],"wordData":[{"word":"People","start":0,"end":6,"coords":[{"x":435.5,"y":294},{"x":491.484375,"y":314}]},{"word":"may","start":6,"end":9,"coords":[{"x":491.484375,"y":294},{"x":467.5,"y":314}]},{"word":"think","start":10,"end":15,"coords":[{"x":533.46875,"y":294},{"x":481.5,"y":314}]},{"word":"their","start":16,"end":21,"coords":[{"x":580.453125,"y":294},{"x":481.5,"y":314}]},{"word":"personal","start":22,"end":30,"coords":[{"x":624.421875,"y":294},{"x":514.484375,"y":314}]},{"word":"situation","start":31,"end":40,"coords":[{"x":702.390625,"y":294},{"x":524.46875,"y":314}]},{"word":"is","start":41,"end":43,"coords":[{"x":778.359375,"y":294},{"x":457.5,"y":314}]},{"word":"better","start":44,"end":50,"coords":[{"x":800.34375,"y":294},{"x":491.484375,"y":314}]},{"word":"than","start":51,"end":55,"coords":[{"x":855.328125,"y":294},{"x":477.5,"y":314}]},{"word":"economic","start":56,"end":64,"coords":[{"x":470.5,"y":319},{"x":514.484375,"y":314}]},{"word":"conditions","start":65,"end":75,"coords":[{"x":553.46875,"y":319},{"x":533.46875,"y":314}]},{"word":"in","start":76,"end":78,"coords":[{"x":640.4375,"y":319},{"x":457.5,"y":314}]},{"word":"their","start":79,"end":84,"coords":[{"x":660.421875,"y":319},{"x":481.5,"y":314}]},{"word":"nation,","start":85,"end":92,"coords":[{"x":701.390625,"y":319},{"x":499.484375,"y":314}]},{"word":"but","start":93,"end":96,"coords":[{"x":762.375,"y":319},{"x":467.5,"y":314}]},{"word":"only","start":97,"end":101,"coords":[{"x":794.375,"y":319},{"x":477.5,"y":314}]},{"word":"in","start":102,"end":104,"coords":[{"x":834.359375,"y":319},{"x":457.5,"y":314}]},{"word":"Brazil","start":105,"end":111,"coords":[{"x":855.34375,"y":319},{"x":491.484375,"y":314}]},{"word":"(72%)","start":112,"end":117,"coords":[{"x":480.453125,"y":344},{"x":481.5,"y":314}]},{"word":"and","start":118,"end":121,"coords":[{"x":537.421875,"y":344},{"x":467.5,"y":314}]},{"word":"China","start":122,"end":127,"coords":[{"x":576.421875,"y":344},{"x":481.5,"y":314}]},{"word":"(70%)","start":128,"end":133,"coords":[{"x":632.390625,"y":344},{"x":481.5,"y":314}]},{"word":"do","start":134,"end":136,"coords":[{"x":689.359375,"y":344},{"x":457.5,"y":314}]},{"word":"large","start":137,"end":142,"coords":[{"x":718.359375,"y":344},{"x":481.5,"y":314}]},{"word":"majorities","start":143,"end":153,"coords":[{"x":768.328125,"y":344},{"x":533.46875,"y":314}]},{"word":"think","start":154,"end":159,"coords":[{"x":855.25,"y":344},{"x":481.5,"y":314}]},{"word":"their","start":160,"end":165,"coords":[{"x":473.484375,"y":369},{"x":481.5,"y":314}]},{"word":"families","start":166,"end":174,"coords":[{"x":514.453125,"y":369},{"x":514.484375,"y":314}]},{"word":"are","start":175,"end":178,"coords":[{"x":581.390625,"y":369},{"x":467.5,"y":314}]},{"word":"better","start":179,"end":185,"coords":[{"x":613.375,"y":369},{"x":491.484375,"y":314}]},{"word":"off","start":186,"end":189,"coords":[{"x":665.359375,"y":369},{"x":467.5,"y":314}]},{"word":"than","start":190,"end":194,"coords":[{"x":691.359375,"y":369},{"x":477.5,"y":314}]},{"word":"they","start":195,"end":199,"coords":[{"x":733.359375,"y":369},{"x":477.5,"y":314}]},{"word":"were","start":200,"end":204,"coords":[{"x":774.359375,"y":369},{"x":477.5,"y":314}]},{"word":"five","start":205,"end":209,"coords":[{"x":820.328125,"y":369},{"x":477.5,"y":314}]},{"word":"years","start":210,"end":215,"coords":[{"x":855.3125,"y":369},{"x":481.5,"y":314}]},{"word":"ago.","start":216,"end":220,"coords":[{"x":479.484375,"y":394},{"x":477.5,"y":314}]},{"word":"On","start":221,"end":223,"coords":[{"x":523.484375,"y":394},{"x":457.5,"y":314}]},{"word":"balance,","start":224,"end":232,"coords":[{"x":556.484375,"y":394},{"x":514.484375,"y":314}]},{"word":"Indians","start":233,"end":240,"coords":[{"x":634.46875,"y":394},{"x":499.484375,"y":314}]},{"word":"(50%)","start":241,"end":246,"coords":[{"x":702.453125,"y":394},{"x":481.5,"y":314}]},{"word":"and","start":247,"end":250,"coords":[{"x":760.421875,"y":394},{"x":467.5,"y":314}]},{"word":"Turks","start":251,"end":256,"coords":[{"x":800.421875,"y":394},{"x":481.5,"y":314}]},{"word":"(43%)","start":257,"end":262,"coords":[{"x":855.390625,"y":394},{"x":481.5,"y":314}]},{"word":"also","start":263,"end":267,"coords":[{"x":483.46875,"y":419},{"x":477.5,"y":314}]},{"word":"say","start":268,"end":271,"coords":[{"x":529.453125,"y":419},{"x":467.5,"y":314}]},{"word":"their","start":272,"end":277,"coords":[{"x":570.453125,"y":419},{"x":481.5,"y":314}]},{"word":"situations","start":278,"end":288,"coords":[{"x":619.421875,"y":419},{"x":533.46875,"y":314}]},{"word":"have","start":289,"end":293,"coords":[{"x":709.390625,"y":419},{"x":477.5,"y":314}]},{"word":"improved.","start":294,"end":303,"coords":[{"x":762.390625,"y":419},{"x":524.46875,"y":314}]},{"word":"However,","start":304,"end":312,"coords":[{"x":855.34375,"y":419},{"x":514.484375,"y":314}]},{"word":"majorities","start":313,"end":323,"coords":[{"x":511.453125,"y":444},{"x":533.46875,"y":314}]},{"word":"or","start":324,"end":326,"coords":[{"x":597.375,"y":444},{"x":457.5,"y":314}]},{"word":"pluralities","start":327,"end":338,"coords":[{"x":622.359375,"y":444},{"x":542.46875,"y":314}]},{"word":"in","start":339,"end":341,"coords":[{"x":707.28125,"y":444},{"x":457.5,"y":314}]},{"word":"9","start":342,"end":343,"coords":[{"x":730.265625,"y":444},{"x":447.5,"y":314}]},{"word":"nations","start":344,"end":351,"coords":[{"x":749.265625,"y":444},{"x":499.484375,"y":314}]},{"word":"say","start":352,"end":355,"coords":[{"x":817.25,"y":444},{"x":467.5,"y":314}]},{"word":"their","start":356,"end":361,"coords":[{"x":855.25,"y":444},{"x":481.5,"y":314}]},{"word":"family","start":362,"end":368,"coords":[{"x":470.46875,"y":469},{"x":491.484375,"y":314}]},{"word":"financial","start":369,"end":378,"coords":[{"x":522.421875,"y":469},{"x":524.46875,"y":314}]},{"word":"situation","start":379,"end":388,"coords":[{"x":594.375,"y":469},{"x":524.46875,"y":314}]},{"word":"has","start":389,"end":392,"coords":[{"x":667.34375,"y":469},{"x":467.5,"y":314}]},{"word":"deteriorated.","start":393,"end":406,"coords":[{"x":702.34375,"y":469},{"x":557.46875,"y":314}]},{"word":"Solid","start":407,"end":412,"coords":[{"x":809.296875,"y":469},{"x":481.5,"y":314}]},{"word":"majorities","start":413,"end":423,"coords":[{"x":855.265625,"y":469},{"x":533.46875,"y":314}]},{"word":"hold","start":424,"end":428,"coords":[{"x":512.421875,"y":494},{"x":477.5,"y":314}]},{"word":"this","start":429,"end":433,"coords":[{"x":556.40625,"y":494},{"x":477.5,"y":314}]},{"word":"view","start":434,"end":438,"coords":[{"x":594.390625,"y":494},{"x":477.5,"y":314}]},{"word":"in","start":439,"end":441,"coords":[{"x":640.359375,"y":494},{"x":457.5,"y":314}]},{"word":"Greece","start":442,"end":448,"coords":[{"x":664.34375,"y":494},{"x":491.484375,"y":314}]},{"word":"(81%),","start":449,"end":455,"coords":[{"x":734.328125,"y":494},{"x":491.484375,"y":314}]},{"word":"Spain","start":456,"end":461,"coords":[{"x":798.296875,"y":494},{"x":481.5,"y":314}]},{"word":"(60%)","start":462,"end":467,"coords":[{"x":855.28125,"y":494},{"x":481.5,"y":314}]},{"word":"and","start":468,"end":471,"coords":[{"x":483.46875,"y":519},{"x":467.5,"y":314}]},{"word":"Pakistan","start":472,"end":480,"coords":[{"x":518.46875,"y":519},{"x":514.484375,"y":314}]},{"word":"(57%),","start":481,"end":487,"coords":[{"x":592.453125,"y":519},{"x":491.484375,"y":314}]},{"word":"as","start":488,"end":490,"coords":[{"x":651.421875,"y":519},{"x":457.5,"y":314}]},{"word":"do","start":491,"end":493,"coords":[{"x":676.421875,"y":519},{"x":457.5,"y":314}]},{"word":"at","start":494,"end":496,"coords":[{"x":702.421875,"y":519},{"x":457.5,"y":314}]},{"word":"least","start":497,"end":502,"coords":[{"x":723.421875,"y":519},{"x":481.5,"y":314}]},{"word":"four-in-ten","start":503,"end":514,"coords":[{"x":767.40625,"y":519},{"x":542.46875,"y":314}]},{"word":"in","start":515,"end":517,"coords":[{"x":855.34375,"y":519},{"x":457.5,"y":314}]},{"word":"Lebanon,","start":518,"end":526,"coords":[{"x":449.484375,"y":544},{"x":514.484375,"y":314}]},{"word":"Italy,","start":527,"end":533,"coords":[{"x":540.484375,"y":544},{"x":491.484375,"y":314}]},{"word":"France,","start":534,"end":541,"coords":[{"x":594.46875,"y":544},{"x":499.484375,"y":314}]},{"word":"Britain,","start":542,"end":550,"coords":[{"x":672.4375,"y":544},{"x":514.484375,"y":314}]},{"word":"the","start":551,"end":554,"coords":[{"x":745.390625,"y":544},{"x":467.5,"y":314}]},{"word":"Czech","start":555,"end":560,"coords":[{"x":787.390625,"y":544},{"x":481.5,"y":314}]},{"word":"Republic,","start":561,"end":570,"coords":[{"x":855.375,"y":544},{"x":524.46875,"y":314}]},{"word":"Japan,","start":571,"end":577,"coords":[{"x":510.453125,"y":569},{"x":491.484375,"y":314}]},{"word":"Egypt","start":578,"end":583,"coords":[{"x":569.453125,"y":569},{"x":481.5,"y":314}]},{"word":"and","start":584,"end":587,"coords":[{"x":620.453125,"y":569},{"x":467.5,"y":314}]},{"word":"Poland.","start":588,"end":595,"coords":[{"x":655.453125,"y":569},{"x":499.484375,"y":314}]}],"filename":"28.json"}